setup.py
src/LEPL.egg-info/PKG-INFO
src/LEPL.egg-info/SOURCES.txt
src/LEPL.egg-info/dependency_links.txt
src/LEPL.egg-info/top_level.txt
src/lepl/__init__.py
src/lepl/_example/__init__.py
src/lepl/_example/args.py
src/lepl/_example/columns.py
src/lepl/_example/config.py
src/lepl/_example/dynamic.py
src/lepl/_example/error.py
src/lepl/_example/expression.py
src/lepl/_example/full_match.py
src/lepl/_example/hello.py
src/lepl/_example/hiren.py
src/lepl/_example/lexer.py
src/lepl/_example/manager.py
src/lepl/_example/matchers.py
src/lepl/_example/memo.py
src/lepl/_example/new_in_4.py
src/lepl/_example/nodes.py
src/lepl/_example/operators.py
src/lepl/_example/performance.py
src/lepl/_example/phone.py
src/lepl/_example/phone_words.py
src/lepl/_example/search.py
src/lepl/_example/search_syntax.py
src/lepl/_example/separators.py
src/lepl/_example/spindrome.py
src/lepl/_example/support.py
src/lepl/_example/trace.py
src/lepl/_example/tutorial_1.py
src/lepl/_example/tutorial_2.py
src/lepl/_example/tutorial_3.py
src/lepl/_example/tutorial_4.py
src/lepl/_test/__init__.py
src/lepl/_test/base.py
src/lepl/_test/bug_stalled_parser.py
src/lepl/_test/magus.py
src/lepl/_test/wrong_cache_bug.py
src/lepl/_test/wrong_depth_bug.py
src/lepl/_test/wrong_regexp_bug.py
src/lepl/apps/__init__.py
src/lepl/apps/json.py
src/lepl/apps/rfc3696.py
src/lepl/apps/_test/__init__.py
src/lepl/apps/_test/json.py
src/lepl/apps/_test/rfc3696.py
src/lepl/bin/__init__.py
src/lepl/bin/bits.py
src/lepl/bin/encode.py
src/lepl/bin/literal.py
src/lepl/bin/matchers.py
src/lepl/bin/_example/__init__.py
src/lepl/bin/_example/literal.py
src/lepl/bin/_test/__init__.py
src/lepl/bin/_test/bits.py
src/lepl/bin/_test/encode.py
src/lepl/bin/_test/literal.py
src/lepl/bin/_test/matchers.py
src/lepl/contrib/__init__.py
src/lepl/contrib/json.py
src/lepl/contrib/matchers.py
src/lepl/core/__init__.py
src/lepl/core/config.py
src/lepl/core/manager.py
src/lepl/core/monitor.py
src/lepl/core/parser.py
src/lepl/core/rewriters.py
src/lepl/core/trace.py
src/lepl/core/_test/__init__.py
src/lepl/core/_test/clone.py
src/lepl/core/_test/config.py
